betterx/__init__.py
betterx/_lsx.py
betterx/_rme.py
betterx/_tshift.py
betterx/utils.py
betterx-1.0.1.data/scripts/lsx
betterx-1.0.1.data/scripts/rme
betterx-1.0.1.data/scripts/tshift
betterx-1.0.1.dist-info/DESCRIPTION.rst
betterx-1.0.1.dist-info/METADATA
betterx-1.0.1.dist-info/RECORD
betterx-1.0.1.dist-info/WHEEL
betterx-1.0.1.dist-info/metadata.json
betterx-1.0.1.dist-info/top_level.txt
