Metadata-Version: 2.0
Name: betterx
Version: 1.0.1
Summary: a better set of tools for unix systems
Home-page: https://github.com/mentix02/betterx
Author: manan
Author-email: manan.yadav02@gmail.com
License: MIT
Platform: UNKNOWN
